CGNS/__config__.py
CGNS/__init__.py
CGNS/version.py
CGNS/MAP/EmbeddedCHLone.cpython-310-x86_64-linux-gnu.so
CGNS/MAP/__init__.py
CGNS/MAP/cgio.py
CGNS/MAP/include/CHLone_config.h
CGNS/MAP/test/__init__.py
CGNS/MAP/test/cgu.py
CGNS/PAT/__init__.py
CGNS/PAT/cgnsclass.py
CGNS/PAT/cgnserrors.py
CGNS/PAT/cgnskeywords.py
CGNS/PAT/cgnslib.py
CGNS/PAT/cgnstypes.py
CGNS/PAT/cgnsutils.py
CGNS/PAT/SIDS/AdditionalFamilyName_t.py
CGNS/PAT/SIDS/ArbitraryGridMotion_t.py
CGNS/PAT/SIDS/Area_t.py
CGNS/PAT/SIDS/AverageInterface_t.py
CGNS/PAT/SIDS/AxiSymmetry_t.py
CGNS/PAT/SIDS/BCDataSet_t.py
CGNS/PAT/SIDS/BCData_t.py
CGNS/PAT/SIDS/BCProperty_t.py
CGNS/PAT/SIDS/BC_t.py
CGNS/PAT/SIDS/BaseIterativeData_t.py
CGNS/PAT/SIDS/CGNSBase_t.py
CGNS/PAT/SIDS/ChemicalKineticModel_t.py
CGNS/PAT/SIDS/ConvergenceHistory_t.py
CGNS/PAT/SIDS/DataArray_t.py
CGNS/PAT/SIDS/DataClass_t.py
CGNS/PAT/SIDS/DataConversion_t.py
CGNS/PAT/SIDS/Descriptor_t.py
CGNS/PAT/SIDS/DimensionalExponents_t.py
CGNS/PAT/SIDS/DimensionalUnits_t.py
CGNS/PAT/SIDS/DiscreteData_t.py
CGNS/PAT/SIDS/EMConductivityModel_t.py
CGNS/PAT/SIDS/EMElectricFieldModel_t.py
CGNS/PAT/SIDS/EMMagneticFieldModel_t.py
CGNS/PAT/SIDS/Elements_t.py
CGNS/PAT/SIDS/FamilyBC_t.py
CGNS/PAT/SIDS/FamilyName_t.py
CGNS/PAT/SIDS/Family_t.py
CGNS/PAT/SIDS/FlowEquationSet_t.py
CGNS/PAT/SIDS/FlowSolution_t.py
CGNS/PAT/SIDS/GasModel_t.py
CGNS/PAT/SIDS/GeometryReference_t.py
CGNS/PAT/SIDS/GoverningEquations_t.py
CGNS/PAT/SIDS/Gravity_t.py
CGNS/PAT/SIDS/GridConnectivity1to1_t.py
CGNS/PAT/SIDS/GridConnectivityProperty_t.py
CGNS/PAT/SIDS/GridConnectivity_t.py
CGNS/PAT/SIDS/GridCoordinates_t.py
CGNS/PAT/SIDS/GridLocation_t.py
CGNS/PAT/SIDS/IntegralData_t.py
CGNS/PAT/SIDS/Ordinal_t.py
CGNS/PAT/SIDS/OversetHoles_t.py
CGNS/PAT/SIDS/PointList_t.py
CGNS/PAT/SIDS/PointRange_t.py
CGNS/PAT/SIDS/ReferenceState_t.py
CGNS/PAT/SIDS/RigidGridMotion_t.py
CGNS/PAT/SIDS/Rind_t.py
CGNS/PAT/SIDS/RotatingCoordinates_t.py
pycgns-6.3.4.dist-info/METADATA
pycgns-6.3.4.dist-info/WHEEL
pycgns-6.3.4.dist-info/entry_points.txt
pycgns-6.3.4.dist-info/RECORD
