Metadata-Version: 2.1
Name: pyCGNS
Version: 6.3.4
Summary: pyCGNS - Python package for CGNS (CFD General Notation System)
Author-Email: "Marc Poinot et al." <marc.poinot@safrangroup.com>
Maintainer-Email: Mickael Philit <mickey.phy@gmail.com>, Marc Poinot <marc.poinot@safrangroup.com>
License: LGPL 2
Classifier: Development Status :: 3 - Alpha
Classifier: Intended Audience :: Developers
Classifier: Intended Audience :: Information Technology
Classifier: Intended Audience :: Science/Research
Classifier: License :: OSI Approved :: GNU Lesser General Public License v2 (LGPLv2)
Classifier: Operating System :: Unix
Classifier: Operating System :: POSIX :: Linux
Classifier: Operating System :: MacOS :: MacOS X
Classifier: Operating System :: Microsoft :: Windows
Classifier: Programming Language :: Cython
Classifier: Programming Language :: Python
Classifier: Programming Language :: Python :: 3
Classifier: Programming Language :: Python :: Implementation :: CPython
Classifier: Topic :: Scientific/Engineering
Classifier: Topic :: Database
Classifier: Topic :: Software Development :: Libraries :: Python Modules
Project-URL: homepage, https://pycgns.github.io/
Project-URL: source, https://github.com/pyCGNS/pyCGNS
Project-URL: documentation, https://pycgns.github.io/
Project-URL: tracker, https://github.com/pyCGNS/pyCGNS/issues
Requires-Python: >=3.10
Requires-Dist: numpy>=1.23.5
Provides-Extra: gui
Requires-Dist: qtpy; extra == "gui"
Requires-Dist: pyside6; extra == "gui"
Requires-Dist: vtk; extra == "gui"
Provides-Extra: test
Requires-Dist: unittest; extra == "test"
